README.rst
setup.py
oxtie/__init__.py
oxtie.egg-info/PKG-INFO
oxtie.egg-info/SOURCES.txt
oxtie.egg-info/dependency_links.txt
oxtie.egg-info/entry_points.txt
oxtie.egg-info/requires.txt
oxtie.egg-info/top_level.txt
oxtie/backs/__init__.py
oxtie/backs/aws.py
oxtie/backs/base.py
oxtie/backs/simple.py
oxtie/fronts/__init__.py
oxtie/fronts/base.py
oxtie/fronts/nums.py
oxtie/fronts/specials.py