Metadata-Version: 1.1
Name: oxtie
Version: 0.1.1
Summary: Tools for saving NoSQL like data to various backends.
Home-page: http://github.com/emin63/oxtie
Author: Emin Martinian
Author-email: emin.martinian@gmail.com
License: MIT
Keywords: nosql persistence database
Platform: UNKNOWN
Classifier: Development Status :: 3 - Alpha
Classifier: Intended Audience :: Developers
Classifier: Programming Language :: Python :: 3
